minidag/__init__.py
minidag/minidag.py
minidag-0.1.1.dist-info/METADATA
minidag-0.1.1.dist-info/WHEEL
minidag-0.1.1.dist-info/licenses/LICENSE
minidag-0.1.1.dist-info/RECORD
