Metadata-Version: 2.3
Name: minidag
Version: 0.1.1
Summary: Small decorator based DAG to orchestrate jobs
Author-email: Paul English <paulnglsh@gmail.com>
License-File: LICENSE
Requires-Python: >=3.8
